LICENSE
MANIFEST.in
README.md
requirements.txt
setup.py
ktool/__init__.py
ktool/__version__.py
ktool/date.py
ktool/file.py
ktool/log.py
ktool/mongo.py
ktool/process.py
ktool/queue.py
ktool/thread.py
ktool/wrapper.py
ktool/xpath.py
ktool.egg-info/PKG-INFO
ktool.egg-info/SOURCES.txt
ktool.egg-info/dependency_links.txt
ktool.egg-info/requires.txt
ktool.egg-info/top_level.txt