Metadata-Version: 2.1
Name: ktool
Version: 1.0.1
Summary: Personal tools
Home-page: https://github.com/kzl_knight/ktool
Author: kzl_knight
Author-email: 164645621@qq.com
License: MIT
Platform: UNKNOWN
Classifier: License :: OSI Approved :: MIT License
Classifier: Programming Language :: Python
Classifier: Programming Language :: Python :: 3
Classifier: Programming Language :: Python :: 3.6
Classifier: Programming Language :: Python :: Implementation :: CPython
Classifier: Programming Language :: Python :: Implementation :: PyPy
Requires-Python: >=3.6.0
